abobjs/__init__.py
abobjs/assertion.py
abobjs/auditable_entity.py
abobjs/auditable_entity_regions.py
abobjs/auditable_entity_types.py
abobjs/base.py
abobjs/buisness_units.py
abobjs/continuous_monitoring_monitor_results.py
abobjs/continuous_monitoring_monitors.py
abobjs/continuous_monitoring_systems.py
abobjs/control.py
abobjs/controlrod.py
abobjs/controls_data.py
abobjs/custom_field.py
abobjs/departments.py
abobjs/effectiveness_option.py
abobjs/entity.py
abobjs/file.py
abobjs/fn_register_cf.py
abobjs/multi.py
abobjs/process.py
abobjs/region.py
abobjs/risk.py
abobjs/status_option.py
abobjs/subprocess.py
abobjs/test.py
abobjs/test_section.py
abobjs/test_type.py
abobjs/user.py
abobjs/vendor_criticalities.py
abobjs/workspace.py
control_rod-2024.8.2.0.dist-info/METADATA
control_rod-2024.8.2.0.dist-info/WHEEL
control_rod-2024.8.2.0.dist-info/top_level.txt
control_rod-2024.8.2.0.dist-info/RECORD
