Metadata-Version: 2.1
Name: control_rod
Version: 2024.8.2.0
Summary: An expiremental auditboard api client
Home-page: https://github.com/soxhub/control_rod
Author: Christopher Halbersma
Author-email: chalbersma@auditboard.com
Classifier: Programming Language :: Python :: 3
Classifier: Operating System :: OS Independent
Requires-Python: >=3.11
Requires-Dist: requests
Requires-Dist: pyjq
Requires-Dist: xmltodict
